xhdata/__init__.py
xhdata/__main__.py
xhdata/Command/__init__.py
xhdata/Command/save_akshare.py
xhdata/Command/save_jq.py
xhdata/Command/save_tdx.py
xhdata/Data/__init__.py
xhdata/Data/jq_style.py
xhdata/Data/stock.py
xhdata/Util/Akshare.py
xhdata/Util/MongoClient.py
xhdata/Util/TransCode.py
xhdata/Util/__init__.py
xhdata-0.0.4.dist-info/METADATA
xhdata-0.0.4.dist-info/WHEEL
xhdata-0.0.4.dist-info/entry_points.txt
xhdata-0.0.4.dist-info/top_level.txt
xhdata-0.0.4.dist-info/RECORD
